README.rst
setup.py
camlipy/__init__.py
camlipy/cli.py
camlipy/directory.py
camlipy/filereader.py
camlipy/filewriter.py
camlipy/rollsum.py
camlipy/schema.py
camlipy/search.py
camlipy.egg-info/PKG-INFO
camlipy.egg-info/SOURCES.txt
camlipy.egg-info/dependency_links.txt
camlipy.egg-info/entry_points.txt
camlipy.egg-info/not-zip-safe
camlipy.egg-info/requires.txt
camlipy.egg-info/top_level.txt
camlipy/tests/__init__.py
camlipy/tests/test_camlipy.py
camlipy/tests/test_camput_and_camget_compatibility.py
camlipy/tests/test_dir.py
camlipy/tests/test_filewriter.py
camlipy/tests/test_rollsum.py
camlipy/tests/test_schema.py