Metadata-Version: 1.1
Name: camlipy
Version: 0.1.1
Summary: UNKNOWN
Home-page: https://github.com/tsileo/camlipy
Author: Thomas Sileo
Author-email: thomas.sileo@gmail.com
License: MIT
Keywords: camlistore storage backups blob
Platform: UNKNOWN
Classifier: Development Status :: 4 - Beta
Classifier: Intended Audience :: Developers
Classifier: Topic :: System :: Archiving :: Backup
Classifier: License :: OSI Approved :: MIT License
Classifier: Programming Language :: Python
